[{"ISO":"QAT","Policy":"E2_Debt\/contract relief","rank":1},{"ISO":"QAT","Policy":"H2_Testing policy","rank":2},{"ISO":"QAT","Policy":"C8_International travel controls","rank":3},{"ISO":"QAT","Policy":"C2_Workplace closing","rank":4},{"ISO":"QAT","Policy":"C3_Cancel public events","rank":5},{"ISO":"QAT","Policy":"C6_Stay at home requirements","rank":6},{"ISO":"QAT","Policy":"H6_Facial Coverings","rank":7},{"ISO":"QAT","Policy":"C7_Restrictions on internal movement","rank":8},{"ISO":"QAT","Policy":"H1_Public information campaigns","rank":9},{"ISO":"QAT","Policy":"C4_Restrictions on gatherings","rank":10},{"ISO":"QAT","Policy":"H7_Vaccination policy","rank":11},{"ISO":"QAT","Policy":"C5_Close public transport","rank":12},{"ISO":"QAT","Policy":"C1_School closing","rank":13},{"ISO":"QAT","Policy":"H3_Contact tracing","rank":14},{"ISO":"QAT","Policy":"E1_Income support","rank":15}]